stylish/__init__.py
stylish/__main__.py
stylish/_version.py
stylish/command_line.py
stylish/filesystem.py
stylish/logging.py
stylish/transform.py
stylish/vgg.py
stylish-0.4.0.dist-info/METADATA
stylish-0.4.0.dist-info/WHEEL
stylish-0.4.0.dist-info/entry_points.txt
stylish-0.4.0.dist-info/top_level.txt
stylish-0.4.0.dist-info/RECORD
